[
  {
    "labels": [
      {
        "wd_id": "Q3476515",
        "search_term": "Bauplastik",
        "confidence": 0.6056
      },
      {
        "wd_id": "Q747567",
        "search_term": "Risalit",
        "confidence": 0.7365
      },
      {
        "aat_id": 300002667,
        "wd_id": "Q831691",
        "search_term": "Geschoss",
        "confidence": 0.6721
      },
      {
        "aat_id": 300003790,
        "wd_id": "Q211775",
        "search_term": "Kanzel",
        "confidence": 0.6266
      },
      {
        "aat_id": 300001324,
        "wd_id": "Q189771",
        "search_term": "Gewölbe",
        "confidence": 0.6006
      },
      {
        "aat_id": 300002526,
        "wd_id": "Q183061",
        "search_term": "Fassade",
        "confidence": 0.6729
      },
      {
        "wd_id": "Q811438",
        "search_term": "Baukörper",
        "confidence": 0.6272
      },
      {
        "wd_id": "Q63759229",
        "search_term": "Seitenflügel",
        "confidence": 0.6187
      },
      {
        "aat_id": 300001280,
        "wd_id": "Q12493",
        "search_term": "Kuppel",
        "confidence": 0.6134
      },
      {
        "aat_id": 300002704,
        "wd_id": "Q695992",
        "search_term": "Wandnische",
        "confidence": 0.6454
      },
      {
        "aat_id": 300001788,
        "wd_id": "Q328092",
        "search_term": "Gesims",
        "confidence": 0.7515
      },
      {
        "aat_id": 300002737,
        "wd_id": "Q175112",
        "search_term": "Pilaster",
        "confidence": 0.7671
      },
      {
        "aat_id": 300002580,
        "wd_id": "Q186637",
        "search_term": "Arkade",
        "confidence": 0.6374
      },
      {
        "aat_id": 300002268,
        "wd_id": "Q163972",
        "search_term": "Dachtraufe",
        "confidence": 0.7099
      }
    ],
    "start": 132,
    "end": 144,
    "found_term": "Sprenggiebel"
  },
  {
    "labels": [
      {
        "wd_id": "Q3476515",
        "search_term": "Bauplastik",
        "confidence": 0.6167
      }
    ],
    "start": 198,
    "end": 209,
    "found_term": "Architektur"
  },
  {
    "labels": [
      {
        "wd_id": "Q3476515",
        "search_term": "Bauplastik",
        "confidence": 0.6167
      }
    ],
    "start": 545,
    "end": 556,
    "found_term": "Architektur"
  },
  {
    "labels": [
      {
        "wd_id": "Q3476515",
        "search_term": "Bauplastik",
        "confidence": 0.7493
      },
      {
        "aat_id": 300004188,
        "wd_id": "Q1125776",
        "search_term": "Gebäudetrakt",
        "confidence": 0.6217
      },
      {
        "wd_id": "Q6149036",
        "search_term": "Dekoration",
        "confidence": 0.641
      },
      {
        "wd_id": "Q747567",
        "search_term": "Risalit",
        "confidence": 0.6392
      },
      {
        "aat_id": 300004324,
        "wd_id": "Q2451751",
        "search_term": "Treppenhaus",
        "confidence": 0.6164
      },
      {
        "aat_id": 300002526,
        "wd_id": "Q183061",
        "search_term": "Fassade",
        "confidence": 0.8396
      },
      {
        "wd_id": "Q811438",
        "search_term": "Baukörper",
        "confidence": 0.7363
      },
      {
        "wd_id": "Q1627767",
        "search_term": "Laubengang",
        "confidence": 0.6255
      },
      {
        "aat_id": 300004792,
        "wd_id": "Q41176",
        "search_term": "Gebäude",
        "confidence": 0.6089
      },
      {
        "aat_id": 300002737,
        "wd_id": "Q175112",
        "search_term": "Pilaster",
        "confidence": 0.6359
      },
      {
        "aat_id": 300002580,
        "wd_id": "Q186637",
        "search_term": "Arkade",
        "confidence": 0.6002
      }
    ],
    "start": 579,
    "end": 597,
    "found_term": "Fassadengestaltung"
  },
  {
    "labels": [
      {
        "wd_id": "Q3476515",
        "search_term": "Bauplastik",
        "confidence": 0.6167
      }
    ],
    "start": 794,
    "end": 805,
    "found_term": "Architektur"
  },
  {
    "labels": [
      {
        "wd_id": "Q3476515",
        "search_term": "Bauplastik",
        "confidence": 0.6167
      }
    ],
    "start": 877,
    "end": 888,
    "found_term": "Architektur"
  },
  {
    "labels": [
      {
        "wd_id": "Q3476515",
        "search_term": "Bauplastik",
        "confidence": 0.619
      }
    ],
    "start": 897,
    "end": 908,
    "found_term": "Historismus"
  },
  {
    "labels": [
      {
        "wd_id": "Q3476515",
        "search_term": "Bauplastik",
        "confidence": 0.6018
      },
      {
        "wd_id": "Q747567",
        "search_term": "Risalit",
        "confidence": 0.7683
      },
      {
        "aat_id": 300004324,
        "wd_id": "Q2451751",
        "search_term": "Treppenhaus",
        "confidence": 0.6317
      },
      {
        "aat_id": 300002526,
        "wd_id": "Q183061",
        "search_term": "Fassade",
        "confidence": 0.7061
      },
      {
        "wd_id": "Q811438",
        "search_term": "Baukörper",
        "confidence": 0.6411
      },
      {
        "wd_id": "Q63759229",
        "search_term": "Seitenflügel",
        "confidence": 0.6195
      },
      {
        "wd_id": "Q1627767",
        "search_term": "Laubengang",
        "confidence": 0.6437
      },
      {
        "aat_id": 300001788,
        "wd_id": "Q328092",
        "search_term": "Gesims",
        "confidence": 0.7254
      },
      {
        "aat_id": 300002737,
        "wd_id": "Q175112",
        "search_term": "Pilaster",
        "confidence": 0.7699
      },
      {
        "aat_id": 300002588,
        "wd_id": "Q170552",
        "search_term": "Balkon",
        "confidence": 0.6024
      },
      {
        "aat_id": 300002580,
        "wd_id": "Q186637",
        "search_term": "Arkade",
        "confidence": 0.6403
      },
      {
        "aat_id": 300002268,
        "wd_id": "Q163972",
        "search_term": "Dachtraufe",
        "confidence": 0.7109
      }
    ],
    "start": 957,
    "end": 967,
    "found_term": "Ziergiebel"
  },
  {
    "labels": [
      {
        "wd_id": "Q3476515",
        "search_term": "Bauplastik",
        "confidence": 0.6054
      },
      {
        "wd_id": "Q747567",
        "search_term": "Risalit",
        "confidence": 0.6427
      },
      {
        "aat_id": 300003725,
        "wd_id": "Q101687",
        "search_term": "Altar",
        "confidence": 0.6354
      },
      {
        "aat_id": 300248835,
        "wd_id": "Q20460",
        "search_term": "Kruzifix",
        "confidence": 0.6532
      },
      {
        "aat_id": 300003790,
        "wd_id": "Q211775",
        "search_term": "Kanzel",
        "confidence": 0.6804
      },
      {
        "aat_id": 300001324,
        "wd_id": "Q189771",
        "search_term": "Gewölbe",
        "confidence": 0.6083
      },
      {
        "aat_id": 300002526,
        "wd_id": "Q183061",
        "search_term": "Fassade",
        "confidence": 0.6313
      },
      {
        "aat_id": 300001280,
        "wd_id": "Q12493",
        "search_term": "Kuppel",
        "confidence": 0.6383
      },
      {
        "wd_id": "Q1501427",
        "search_term": "Oktogon",
        "confidence": 0.6638
      },
      {
        "aat_id": 300002704,
        "wd_id": "Q695992",
        "search_term": "Wandnische",
        "confidence": 0.6968
      },
      {
        "aat_id": 300001788,
        "wd_id": "Q328092",
        "search_term": "Gesims",
        "confidence": 0.7219
      },
      {
        "aat_id": 300002737,
        "wd_id": "Q175112",
        "search_term": "Pilaster",
        "confidence": 0.732
      },
      {
        "aat_id": 300002580,
        "wd_id": "Q186637",
        "search_term": "Arkade",
        "confidence": 0.6317
      },
      {
        "aat_id": 300002268,
        "wd_id": "Q163972",
        "search_term": "Dachtraufe",
        "confidence": 0.6521
      }
    ],
    "start": 984,
    "end": 993,
    "found_term": "Bekrönung"
  },
  {
    "labels": [
      {
        "wd_id": "Q3476515",
        "search_term": "Bauplastik",
        "confidence": 0.6167
      }
    ],
    "start": 1066,
    "end": 1077,
    "found_term": "Architektur"
  },
  {
    "labels": [
      {
        "wd_id": "Q3476515",
        "search_term": "Bauplastik",
        "confidence": 0.6167
      }
    ],
    "start": 1207,
    "end": 1218,
    "found_term": "Architektur"
  },
  {
    "labels": [
      {
        "wd_id": "Q3476515",
        "search_term": "Bauplastik",
        "confidence": 0.6167
      }
    ],
    "start": 1388,
    "end": 1399,
    "found_term": "Architektur"
  },
  {
    "labels": [
      {
        "wd_id": "Q3476515",
        "search_term": "Bauplastik",
        "confidence": 0.619
      }
    ],
    "start": 1535,
    "end": 1546,
    "found_term": "Historismus"
  },
  {
    "labels": [
      {
        "wd_id": "Q3476515",
        "search_term": "Bauplastik",
        "confidence": 0.6167
      }
    ],
    "start": 1675,
    "end": 1686,
    "found_term": "Architektur"
  },
  {
    "labels": [
      {
        "wd_id": "Q3476515",
        "search_term": "Bauplastik",
        "confidence": 0.6056
      },
      {
        "wd_id": "Q747567",
        "search_term": "Risalit",
        "confidence": 0.7365
      },
      {
        "aat_id": 300002667,
        "wd_id": "Q831691",
        "search_term": "Geschoss",
        "confidence": 0.6721
      },
      {
        "aat_id": 300003790,
        "wd_id": "Q211775",
        "search_term": "Kanzel",
        "confidence": 0.6266
      },
      {
        "aat_id": 300001324,
        "wd_id": "Q189771",
        "search_term": "Gewölbe",
        "confidence": 0.6006
      },
      {
        "aat_id": 300002526,
        "wd_id": "Q183061",
        "search_term": "Fassade",
        "confidence": 0.6729
      },
      {
        "wd_id": "Q811438",
        "search_term": "Baukörper",
        "confidence": 0.6272
      },
      {
        "wd_id": "Q63759229",
        "search_term": "Seitenflügel",
        "confidence": 0.6187
      },
      {
        "aat_id": 300001280,
        "wd_id": "Q12493",
        "search_term": "Kuppel",
        "confidence": 0.6134
      },
      {
        "aat_id": 300002704,
        "wd_id": "Q695992",
        "search_term": "Wandnische",
        "confidence": 0.6454
      },
      {
        "aat_id": 300001788,
        "wd_id": "Q328092",
        "search_term": "Gesims",
        "confidence": 0.7515
      },
      {
        "aat_id": 300002737,
        "wd_id": "Q175112",
        "search_term": "Pilaster",
        "confidence": 0.7671
      },
      {
        "aat_id": 300002580,
        "wd_id": "Q186637",
        "search_term": "Arkade",
        "confidence": 0.6374
      },
      {
        "aat_id": 300002268,
        "wd_id": "Q163972",
        "search_term": "Dachtraufe",
        "confidence": 0.7099
      }
    ],
    "start": 1802,
    "end": 1814,
    "found_term": "Sprenggiebel"
  },
  {
    "labels": [
      {
        "wd_id": "Q3476515",
        "search_term": "Bauplastik",
        "confidence": 0.6167
      }
    ],
    "start": 1858,
    "end": 1869,
    "found_term": "Architektur"
  },
  {
    "labels": [
      {
        "wd_id": "Q3476515",
        "search_term": "Bauplastik",
        "confidence": 0.6167
      }
    ],
    "start": 1961,
    "end": 1972,
    "found_term": "Architektur"
  },
  {
    "labels": [
      {
        "wd_id": "Q3476515",
        "search_term": "Bauplastik",
        "confidence": 0.6056
      },
      {
        "wd_id": "Q747567",
        "search_term": "Risalit",
        "confidence": 0.7365
      },
      {
        "aat_id": 300002667,
        "wd_id": "Q831691",
        "search_term": "Geschoss",
        "confidence": 0.6721
      },
      {
        "aat_id": 300003790,
        "wd_id": "Q211775",
        "search_term": "Kanzel",
        "confidence": 0.6266
      },
      {
        "aat_id": 300001324,
        "wd_id": "Q189771",
        "search_term": "Gewölbe",
        "confidence": 0.6006
      },
      {
        "aat_id": 300002526,
        "wd_id": "Q183061",
        "search_term": "Fassade",
        "confidence": 0.6729
      },
      {
        "wd_id": "Q811438",
        "search_term": "Baukörper",
        "confidence": 0.6272
      },
      {
        "wd_id": "Q63759229",
        "search_term": "Seitenflügel",
        "confidence": 0.6187
      },
      {
        "aat_id": 300001280,
        "wd_id": "Q12493",
        "search_term": "Kuppel",
        "confidence": 0.6134
      },
      {
        "aat_id": 300002704,
        "wd_id": "Q695992",
        "search_term": "Wandnische",
        "confidence": 0.6454
      },
      {
        "aat_id": 300001788,
        "wd_id": "Q328092",
        "search_term": "Gesims",
        "confidence": 0.7515
      },
      {
        "aat_id": 300002737,
        "wd_id": "Q175112",
        "search_term": "Pilaster",
        "confidence": 0.7671
      },
      {
        "aat_id": 300002580,
        "wd_id": "Q186637",
        "search_term": "Arkade",
        "confidence": 0.6374
      },
      {
        "aat_id": 300002268,
        "wd_id": "Q163972",
        "search_term": "Dachtraufe",
        "confidence": 0.7099
      }
    ],
    "start": 2016,
    "end": 2028,
    "found_term": "Sprenggiebel"
  },
  {
    "labels": [
      {
        "wd_id": "Q3476515",
        "search_term": "Bauplastik",
        "confidence": 0.6167
      }
    ],
    "start": 2072,
    "end": 2083,
    "found_term": "Architektur"
  },
  {
    "labels": [
      {
        "wd_id": "Q3476515",
        "search_term": "Bauplastik",
        "confidence": 0.6056
      },
      {
        "wd_id": "Q747567",
        "search_term": "Risalit",
        "confidence": 0.7365
      },
      {
        "aat_id": 300002667,
        "wd_id": "Q831691",
        "search_term": "Geschoss",
        "confidence": 0.6721
      },
      {
        "aat_id": 300003790,
        "wd_id": "Q211775",
        "search_term": "Kanzel",
        "confidence": 0.6266
      },
      {
        "aat_id": 300001324,
        "wd_id": "Q189771",
        "search_term": "Gewölbe",
        "confidence": 0.6006
      },
      {
        "aat_id": 300002526,
        "wd_id": "Q183061",
        "search_term": "Fassade",
        "confidence": 0.6729
      },
      {
        "wd_id": "Q811438",
        "search_term": "Baukörper",
        "confidence": 0.6272
      },
      {
        "wd_id": "Q63759229",
        "search_term": "Seitenflügel",
        "confidence": 0.6187
      },
      {
        "aat_id": 300001280,
        "wd_id": "Q12493",
        "search_term": "Kuppel",
        "confidence": 0.6134
      },
      {
        "aat_id": 300002704,
        "wd_id": "Q695992",
        "search_term": "Wandnische",
        "confidence": 0.6454
      },
      {
        "aat_id": 300001788,
        "wd_id": "Q328092",
        "search_term": "Gesims",
        "confidence": 0.7515
      },
      {
        "aat_id": 300002737,
        "wd_id": "Q175112",
        "search_term": "Pilaster",
        "confidence": 0.7671
      },
      {
        "aat_id": 300002580,
        "wd_id": "Q186637",
        "search_term": "Arkade",
        "confidence": 0.6374
      },
      {
        "aat_id": 300002268,
        "wd_id": "Q163972",
        "search_term": "Dachtraufe",
        "confidence": 0.7099
      }
    ],
    "start": 2105,
    "end": 2117,
    "found_term": "Sprenggiebel"
  },
  {
    "labels": [
      {
        "wd_id": "Q3476515",
        "search_term": "Bauplastik",
        "confidence": 0.6167
      }
    ],
    "start": 2172,
    "end": 2183,
    "found_term": "Architektur"
  },
  {
    "labels": [
      {
        "aat_id": 300002944,
        "wd_id": "Q35473",
        "search_term": "Fenster",
        "confidence": 0.6322
      },
      {
        "wd_id": "Q747567",
        "search_term": "Risalit",
        "confidence": 0.7708
      },
      {
        "aat_id": 300004324,
        "wd_id": "Q2451751",
        "search_term": "Treppenhaus",
        "confidence": 0.6294
      },
      {
        "aat_id": 300001324,
        "wd_id": "Q189771",
        "search_term": "Gewölbe",
        "confidence": 0.6014
      },
      {
        "aat_id": 300002526,
        "wd_id": "Q183061",
        "search_term": "Fassade",
        "confidence": 0.7318
      },
      {
        "wd_id": "Q811438",
        "search_term": "Baukörper",
        "confidence": 0.6561
      },
      {
        "wd_id": "Q63759229",
        "search_term": "Seitenflügel",
        "confidence": 0.6696
      },
      {
        "wd_id": "Q1627767",
        "search_term": "Laubengang",
        "confidence": 0.6125
      },
      {
        "aat_id": 300002704,
        "wd_id": "Q695992",
        "search_term": "Wandnische",
        "confidence": 0.6123
      },
      {
        "aat_id": 300001788,
        "wd_id": "Q328092",
        "search_term": "Gesims",
        "confidence": 0.7559
      },
      {
        "aat_id": 300002737,
        "wd_id": "Q175112",
        "search_term": "Pilaster",
        "confidence": 0.7459
      },
      {
        "aat_id": 300002580,
        "wd_id": "Q186637",
        "search_term": "Arkade",
        "confidence": 0.6765
      },
      {
        "aat_id": 300002268,
        "wd_id": "Q163972",
        "search_term": "Dachtraufe",
        "confidence": 0.7419
      }
    ],
    "start": 31,
    "end": 37,
    "found_term": "Giebel"
  },
  {
    "labels": [
      {
        "aat_id": 300002944,
        "wd_id": "Q35473",
        "search_term": "Fenster",
        "confidence": 0.6322
      },
      {
        "wd_id": "Q747567",
        "search_term": "Risalit",
        "confidence": 0.7708
      },
      {
        "aat_id": 300004324,
        "wd_id": "Q2451751",
        "search_term": "Treppenhaus",
        "confidence": 0.6294
      },
      {
        "aat_id": 300001324,
        "wd_id": "Q189771",
        "search_term": "Gewölbe",
        "confidence": 0.6014
      },
      {
        "aat_id": 300002526,
        "wd_id": "Q183061",
        "search_term": "Fassade",
        "confidence": 0.7318
      },
      {
        "wd_id": "Q811438",
        "search_term": "Baukörper",
        "confidence": 0.6561
      },
      {
        "wd_id": "Q63759229",
        "search_term": "Seitenflügel",
        "confidence": 0.6696
      },
      {
        "wd_id": "Q1627767",
        "search_term": "Laubengang",
        "confidence": 0.6125
      },
      {
        "aat_id": 300002704,
        "wd_id": "Q695992",
        "search_term": "Wandnische",
        "confidence": 0.6123
      },
      {
        "aat_id": 300001788,
        "wd_id": "Q328092",
        "search_term": "Gesims",
        "confidence": 0.7559
      },
      {
        "aat_id": 300002737,
        "wd_id": "Q175112",
        "search_term": "Pilaster",
        "confidence": 0.7459
      },
      {
        "aat_id": 300002580,
        "wd_id": "Q186637",
        "search_term": "Arkade",
        "confidence": 0.6765
      },
      {
        "aat_id": 300002268,
        "wd_id": "Q163972",
        "search_term": "Dachtraufe",
        "confidence": 0.7419
      }
    ],
    "start": 120,
    "end": 126,
    "found_term": "Giebel"
  },
  {
    "labels": [
      {
        "aat_id": 300002944,
        "wd_id": "Q35473",
        "search_term": "Fenster",
        "confidence": 0.6322
      },
      {
        "wd_id": "Q747567",
        "search_term": "Risalit",
        "confidence": 0.7708
      },
      {
        "aat_id": 300004324,
        "wd_id": "Q2451751",
        "search_term": "Treppenhaus",
        "confidence": 0.6294
      },
      {
        "aat_id": 300001324,
        "wd_id": "Q189771",
        "search_term": "Gewölbe",
        "confidence": 0.6014
      },
      {
        "aat_id": 300002526,
        "wd_id": "Q183061",
        "search_term": "Fassade",
        "confidence": 0.7318
      },
      {
        "wd_id": "Q811438",
        "search_term": "Baukörper",
        "confidence": 0.6561
      },
      {
        "wd_id": "Q63759229",
        "search_term": "Seitenflügel",
        "confidence": 0.6696
      },
      {
        "wd_id": "Q1627767",
        "search_term": "Laubengang",
        "confidence": 0.6125
      },
      {
        "aat_id": 300002704,
        "wd_id": "Q695992",
        "search_term": "Wandnische",
        "confidence": 0.6123
      },
      {
        "aat_id": 300001788,
        "wd_id": "Q328092",
        "search_term": "Gesims",
        "confidence": 0.7559
      },
      {
        "aat_id": 300002737,
        "wd_id": "Q175112",
        "search_term": "Pilaster",
        "confidence": 0.7459
      },
      {
        "aat_id": 300002580,
        "wd_id": "Q186637",
        "search_term": "Arkade",
        "confidence": 0.6765
      },
      {
        "aat_id": 300002268,
        "wd_id": "Q163972",
        "search_term": "Dachtraufe",
        "confidence": 0.7419
      }
    ],
    "start": 166,
    "end": 172,
    "found_term": "Giebel"
  },
  {
    "labels": [
      {
        "aat_id": 300002944,
        "wd_id": "Q35473",
        "search_term": "Fenster",
        "confidence": 0.6322
      },
      {
        "wd_id": "Q747567",
        "search_term": "Risalit",
        "confidence": 0.7708
      },
      {
        "aat_id": 300004324,
        "wd_id": "Q2451751",
        "search_term": "Treppenhaus",
        "confidence": 0.6294
      },
      {
        "aat_id": 300001324,
        "wd_id": "Q189771",
        "search_term": "Gewölbe",
        "confidence": 0.6014
      },
      {
        "aat_id": 300002526,
        "wd_id": "Q183061",
        "search_term": "Fassade",
        "confidence": 0.7318
      },
      {
        "wd_id": "Q811438",
        "search_term": "Baukörper",
        "confidence": 0.6561
      },
      {
        "wd_id": "Q63759229",
        "search_term": "Seitenflügel",
        "confidence": 0.6696
      },
      {
        "wd_id": "Q1627767",
        "search_term": "Laubengang",
        "confidence": 0.6125
      },
      {
        "aat_id": 300002704,
        "wd_id": "Q695992",
        "search_term": "Wandnische",
        "confidence": 0.6123
      },
      {
        "aat_id": 300001788,
        "wd_id": "Q328092",
        "search_term": "Gesims",
        "confidence": 0.7559
      },
      {
        "aat_id": 300002737,
        "wd_id": "Q175112",
        "search_term": "Pilaster",
        "confidence": 0.7459
      },
      {
        "aat_id": 300002580,
        "wd_id": "Q186637",
        "search_term": "Arkade",
        "confidence": 0.6765
      },
      {
        "aat_id": 300002268,
        "wd_id": "Q163972",
        "search_term": "Dachtraufe",
        "confidence": 0.7419
      }
    ],
    "start": 252,
    "end": 258,
    "found_term": "Giebel"
  },
  {
    "labels": [
      {
        "aat_id": 300002944,
        "wd_id": "Q35473",
        "search_term": "Fenster",
        "confidence": 0.6322
      },
      {
        "wd_id": "Q747567",
        "search_term": "Risalit",
        "confidence": 0.7708
      },
      {
        "aat_id": 300004324,
        "wd_id": "Q2451751",
        "search_term": "Treppenhaus",
        "confidence": 0.6294
      },
      {
        "aat_id": 300001324,
        "wd_id": "Q189771",
        "search_term": "Gewölbe",
        "confidence": 0.6014
      },
      {
        "aat_id": 300002526,
        "wd_id": "Q183061",
        "search_term": "Fassade",
        "confidence": 0.7318
      },
      {
        "wd_id": "Q811438",
        "search_term": "Baukörper",
        "confidence": 0.6561
      },
      {
        "wd_id": "Q63759229",
        "search_term": "Seitenflügel",
        "confidence": 0.6696
      },
      {
        "wd_id": "Q1627767",
        "search_term": "Laubengang",
        "confidence": 0.6125
      },
      {
        "aat_id": 300002704,
        "wd_id": "Q695992",
        "search_term": "Wandnische",
        "confidence": 0.6123
      },
      {
        "aat_id": 300001788,
        "wd_id": "Q328092",
        "search_term": "Gesims",
        "confidence": 0.7559
      },
      {
        "aat_id": 300002737,
        "wd_id": "Q175112",
        "search_term": "Pilaster",
        "confidence": 0.7459
      },
      {
        "aat_id": 300002580,
        "wd_id": "Q186637",
        "search_term": "Arkade",
        "confidence": 0.6765
      },
      {
        "aat_id": 300002268,
        "wd_id": "Q163972",
        "search_term": "Dachtraufe",
        "confidence": 0.7419
      }
    ],
    "start": 515,
    "end": 521,
    "found_term": "Giebel"
  },
  {
    "labels": [
      {
        "aat_id": 300002944,
        "wd_id": "Q35473",
        "search_term": "Fenster",
        "confidence": 0.8803
      },
      {
        "wd_id": "Q747567",
        "search_term": "Risalit",
        "confidence": 0.6675
      },
      {
        "aat_id": 300004324,
        "wd_id": "Q2451751",
        "search_term": "Treppenhaus",
        "confidence": 0.6684
      },
      {
        "aat_id": 300001324,
        "wd_id": "Q189771",
        "search_term": "Gewölbe",
        "confidence": 0.6333
      },
      {
        "aat_id": 300002526,
        "wd_id": "Q183061",
        "search_term": "Fassade",
        "confidence": 0.682
      },
      {
        "wd_id": "Q811438",
        "search_term": "Baukörper",
        "confidence": 0.6141
      },
      {
        "wd_id": "Q63759229",
        "search_term": "Seitenflügel",
        "confidence": 0.6136
      },
      {
        "aat_id": 300002803,
        "wd_id": "Q36794",
        "search_term": "Tür",
        "confidence": 0.6448
      },
      {
        "aat_id": 300002704,
        "wd_id": "Q695992",
        "search_term": "Wandnische",
        "confidence": 0.6132
      },
      {
        "aat_id": 300002060,
        "wd_id": "Q217164",
        "search_term": "Fußboden",
        "confidence": 0.6127
      },
      {
        "aat_id": 300001788,
        "wd_id": "Q328092",
        "search_term": "Gesims",
        "confidence": 0.69
      },
      {
        "aat_id": 300002737,
        "wd_id": "Q175112",
        "search_term": "Pilaster",
        "confidence": 0.6839
      },
      {
        "aat_id": 300002588,
        "wd_id": "Q170552",
        "search_term": "Balkon",
        "confidence": 0.6195
      },
      {
        "aat_id": 300002580,
        "wd_id": "Q186637",
        "search_term": "Arkade",
        "confidence": 0.6391
      },
      {
        "aat_id": 300002268,
        "wd_id": "Q163972",
        "search_term": "Dachtraufe",
        "confidence": 0.7166
      }
    ],
    "start": 1014,
    "end": 1022,
    "found_term": "Fenstern"
  },
  {
    "labels": [
      {
        "aat_id": 300002944,
        "wd_id": "Q35473",
        "search_term": "Fenster",
        "confidence": 0.7144
      },
      {
        "aat_id": 300002803,
        "wd_id": "Q36794",
        "search_term": "Tür",
        "confidence": 0.782
      }
    ],
    "start": 1027,
    "end": 1032,
    "found_term": "Türen"
  },
  {
    "labels": [
      {
        "aat_id": 300002944,
        "wd_id": "Q35473",
        "search_term": "Fenster",
        "confidence": 0.6322
      },
      {
        "wd_id": "Q747567",
        "search_term": "Risalit",
        "confidence": 0.7708
      },
      {
        "aat_id": 300004324,
        "wd_id": "Q2451751",
        "search_term": "Treppenhaus",
        "confidence": 0.6294
      },
      {
        "aat_id": 300001324,
        "wd_id": "Q189771",
        "search_term": "Gewölbe",
        "confidence": 0.6014
      },
      {
        "aat_id": 300002526,
        "wd_id": "Q183061",
        "search_term": "Fassade",
        "confidence": 0.7318
      },
      {
        "wd_id": "Q811438",
        "search_term": "Baukörper",
        "confidence": 0.6561
      },
      {
        "wd_id": "Q63759229",
        "search_term": "Seitenflügel",
        "confidence": 0.6696
      },
      {
        "wd_id": "Q1627767",
        "search_term": "Laubengang",
        "confidence": 0.6125
      },
      {
        "aat_id": 300002704,
        "wd_id": "Q695992",
        "search_term": "Wandnische",
        "confidence": 0.6123
      },
      {
        "aat_id": 300001788,
        "wd_id": "Q328092",
        "search_term": "Gesims",
        "confidence": 0.7559
      },
      {
        "aat_id": 300002737,
        "wd_id": "Q175112",
        "search_term": "Pilaster",
        "confidence": 0.7459
      },
      {
        "aat_id": 300002580,
        "wd_id": "Q186637",
        "search_term": "Arkade",
        "confidence": 0.6765
      },
      {
        "aat_id": 300002268,
        "wd_id": "Q163972",
        "search_term": "Dachtraufe",
        "confidence": 0.7419
      }
    ],
    "start": 1426,
    "end": 1432,
    "found_term": "Giebel"
  },
  {
    "labels": [
      {
        "aat_id": 300002944,
        "wd_id": "Q35473",
        "search_term": "Fenster",
        "confidence": 0.6322
      },
      {
        "wd_id": "Q747567",
        "search_term": "Risalit",
        "confidence": 0.7708
      },
      {
        "aat_id": 300004324,
        "wd_id": "Q2451751",
        "search_term": "Treppenhaus",
        "confidence": 0.6294
      },
      {
        "aat_id": 300001324,
        "wd_id": "Q189771",
        "search_term": "Gewölbe",
        "confidence": 0.6014
      },
      {
        "aat_id": 300002526,
        "wd_id": "Q183061",
        "search_term": "Fassade",
        "confidence": 0.7318
      },
      {
        "wd_id": "Q811438",
        "search_term": "Baukörper",
        "confidence": 0.6561
      },
      {
        "wd_id": "Q63759229",
        "search_term": "Seitenflügel",
        "confidence": 0.6696
      },
      {
        "wd_id": "Q1627767",
        "search_term": "Laubengang",
        "confidence": 0.6125
      },
      {
        "aat_id": 300002704,
        "wd_id": "Q695992",
        "search_term": "Wandnische",
        "confidence": 0.6123
      },
      {
        "aat_id": 300001788,
        "wd_id": "Q328092",
        "search_term": "Gesims",
        "confidence": 0.7559
      },
      {
        "aat_id": 300002737,
        "wd_id": "Q175112",
        "search_term": "Pilaster",
        "confidence": 0.7459
      },
      {
        "aat_id": 300002580,
        "wd_id": "Q186637",
        "search_term": "Arkade",
        "confidence": 0.6765
      },
      {
        "aat_id": 300002268,
        "wd_id": "Q163972",
        "search_term": "Dachtraufe",
        "confidence": 0.7419
      }
    ],
    "start": 2237,
    "end": 2243,
    "found_term": "Giebel"
  },
  {
    "labels": [
      {
        "wd_id": "Q747567",
        "search_term": "Risalit",
        "confidence": 0.7194
      },
      {
        "aat_id": 300002526,
        "wd_id": "Q183061",
        "search_term": "Fassade",
        "confidence": 0.6839
      },
      {
        "wd_id": "Q811438",
        "search_term": "Baukörper",
        "confidence": 0.6043
      },
      {
        "wd_id": "Q63759229",
        "search_term": "Seitenflügel",
        "confidence": 0.6293
      },
      {
        "aat_id": 300001788,
        "wd_id": "Q328092",
        "search_term": "Gesims",
        "confidence": 0.728
      },
      {
        "aat_id": 300002737,
        "wd_id": "Q175112",
        "search_term": "Pilaster",
        "confidence": 0.703
      },
      {
        "aat_id": 300002580,
        "wd_id": "Q186637",
        "search_term": "Arkade",
        "confidence": 0.6301
      },
      {
        "aat_id": 300002268,
        "wd_id": "Q163972",
        "search_term": "Dachtraufe",
        "confidence": 0.7394
      }
    ],
    "start": 844,
    "end": 851,
    "found_term": "Giebels"
  },
  {
    "labels": [
      {
        "wd_id": "Q747567",
        "search_term": "Risalit",
        "confidence": 0.7289
      },
      {
        "aat_id": 300004324,
        "wd_id": "Q2451751",
        "search_term": "Treppenhaus",
        "confidence": 0.6169
      },
      {
        "aat_id": 300002526,
        "wd_id": "Q183061",
        "search_term": "Fassade",
        "confidence": 0.7021
      },
      {
        "wd_id": "Q811438",
        "search_term": "Baukörper",
        "confidence": 0.6123
      },
      {
        "aat_id": 300002704,
        "wd_id": "Q695992",
        "search_term": "Wandnische",
        "confidence": 0.6018
      },
      {
        "aat_id": 300001788,
        "wd_id": "Q328092",
        "search_term": "Gesims",
        "confidence": 0.7341
      },
      {
        "aat_id": 300002737,
        "wd_id": "Q175112",
        "search_term": "Pilaster",
        "confidence": 0.7573
      },
      {
        "aat_id": 300002580,
        "wd_id": "Q186637",
        "search_term": "Arkade",
        "confidence": 0.6421
      },
      {
        "aat_id": 300002268,
        "wd_id": "Q163972",
        "search_term": "Dachtraufe",
        "confidence": 0.741
      }
    ],
    "start": 999,
    "end": 1009,
    "found_term": "Verdachung"
  },
  {
    "labels": [
      {
        "wd_id": "Q747567",
        "search_term": "Risalit",
        "confidence": 0.7007
      },
      {
        "aat_id": 300248835,
        "wd_id": "Q20460",
        "search_term": "Kruzifix",
        "confidence": 0.6099
      },
      {
        "aat_id": 300003790,
        "wd_id": "Q211775",
        "search_term": "Kanzel",
        "confidence": 0.6097
      },
      {
        "aat_id": 300037647,
        "wd_id": "Q862454",
        "search_term": "Laterne",
        "confidence": 0.6477
      },
      {
        "aat_id": 300002526,
        "wd_id": "Q183061",
        "search_term": "Fassade",
        "confidence": 0.6282
      },
      {
        "wd_id": "Q811438",
        "search_term": "Baukörper",
        "confidence": 0.6032
      },
      {
        "aat_id": 300001280,
        "wd_id": "Q12493",
        "search_term": "Kuppel",
        "confidence": 0.6255
      },
      {
        "wd_id": "Q1501427",
        "search_term": "Oktogon",
        "confidence": 0.6781
      },
      {
        "aat_id": 300002704,
        "wd_id": "Q695992",
        "search_term": "Wandnische",
        "confidence": 0.6471
      },
      {
        "aat_id": 300001788,
        "wd_id": "Q328092",
        "search_term": "Gesims",
        "confidence": 0.7533
      },
      {
        "aat_id": 300002737,
        "wd_id": "Q175112",
        "search_term": "Pilaster",
        "confidence": 0.7612
      },
      {
        "aat_id": 300002580,
        "wd_id": "Q186637",
        "search_term": "Arkade",
        "confidence": 0.641
      },
      {
        "aat_id": 300002268,
        "wd_id": "Q163972",
        "search_term": "Dachtraufe",
        "confidence": 0.6782
      }
    ],
    "start": 1578,
    "end": 1585,
    "found_term": "bekrönt"
  }
]